/*
** $Id: lopcodes.c,v 1.37.1.1 2007/12/27 13:02:25 roberto Exp $
** See Copyright Notice in lua.h
*/


#define lopcodes_c
#define LUA_CORE


#include "lopcodes.h"


/* ORDER OP */

const char *const luaP_opnames[46] = {
  "MOVE", // 1
  "LOADK", // 2
  "LOADBOOL", // 3
  "LOADNIL", // 4
  "GETUPVAL", // 5
  "GETGLOBAL", // 6
  "GETTABLE", // 7 
  "SETGLOBAL", // 8 
  "SETUPVAL", // 9 
  "SETTABLE", // 10 
  "NEWTABLE", // 11
  "SELF", // 12 
  "ADD", // 13
  "SUB", // 14
  "MUL", // 15
  "DIV", // 16
  "MOD", // 17 
  "POW", // 18 
  "BOR", // 19 
  "BAND", // 20
  "BXOR", // 21
  "BLSHFT", // 22
  "BRSHFT", // 23
  "BNOT", // 24
  "INTDIV", // 25
  "UNM", // 26
  "NOT", // 27
  "LEN", // 28
  "CONCAT", // 29
  "JMP", // 30
  "EQ", // 31
  "LT", // 32
  "LE", // 33
  "TEST", // 34
  "TESTSET", // 35
  "CALL", // 36
  "TAILCALL", // 37
  "RETURN", // 38
  "FORLOOP", // 39
  "FORPREP", // 40
  "TFORLOOP", // 41
  "SETLIST", // 42
  "CLOSE", // 43
  "CLOSURE", // 44
  "VARARG", // 45
  NULL
};


#define opmode(t,a,b,c,m) (((t)<<7) | ((a)<<6) | ((b)<<4) | ((c)<<2) | (m))

const lu_byte luaP_opmodes[45] = {
/*       T  A    B       C     mode		   opcode	*/
  opmode(0, 1, OpArgR, OpArgN, iABC) 		/* OP_MOVE */
 ,opmode(0, 1, OpArgK, OpArgN, iABx)		/* OP_LOADK */
 ,opmode(0, 1, OpArgU, OpArgU, iABC)		/* OP_LOADBOOL */
 ,opmode(0, 1, OpArgR, OpArgN, iABC)		/* OP_LOADNIL */
 ,opmode(0, 1, OpArgU, OpArgN, iABC)		/* OP_GETUPVAL */
 ,opmode(0, 1, OpArgK, OpArgN, iABx)		/* OP_GETGLOBAL */
 ,opmode(0, 1, OpArgR, OpArgK, iABC)		/* OP_GETTABLE */
 ,opmode(0, 0, OpArgK, OpArgN, iABx)		/* OP_SETGLOBAL */
 ,opmode(0, 0, OpArgU, OpArgN, iABC)		/* OP_SETUPVAL */
 ,opmode(0, 0, OpArgK, OpArgK, iABC)		/* OP_SETTABLE */
 ,opmode(0, 1, OpArgU, OpArgU, iABC)		/* OP_NEWTABLE */
 ,opmode(0, 1, OpArgR, OpArgK, iABC)		/* OP_SELF */
 ,opmode(0, 1, OpArgK, OpArgK, iABC)		/* OP_ADD */
 ,opmode(0, 1, OpArgK, OpArgK, iABC)		/* OP_SUB */
 ,opmode(0, 1, OpArgK, OpArgK, iABC)		/* OP_MUL */
 ,opmode(0, 1, OpArgK, OpArgK, iABC)		/* OP_DIV */
 ,opmode(0, 1, OpArgK, OpArgK, iABC)		/* OP_MOD */
 ,opmode(0, 1, OpArgK, OpArgK, iABC)		/* OP_POW */
 ,opmode(0, 1, OpArgK, OpArgK, iABC)		/* OP_BOR */
 ,opmode(0, 1, OpArgK, OpArgK, iABC)		/* OP_BAND */
 ,opmode(0, 1, OpArgK, OpArgK, iABC)		/* OP_BXOR */
 ,opmode(0, 1, OpArgK, OpArgK, iABC)		/* OP_BLSHFT */
 ,opmode(0, 1, OpArgK, OpArgK, iABC)		/* OP_BRSHFT */
 ,opmode(0, 1, OpArgR, OpArgN, iABC)		/* OP_BNOT */
 ,opmode(0, 1, OpArgK, OpArgK, iABC)		/* OP_INTDIV */
 ,opmode(0, 1, OpArgR, OpArgN, iABC)		/* OP_UNM */
 ,opmode(0, 1, OpArgR, OpArgN, iABC)		/* OP_NOT */
 ,opmode(0, 1, OpArgR, OpArgN, iABC)		/* OP_LEN */
 ,opmode(0, 1, OpArgR, OpArgR, iABC)		/* OP_CONCAT */
 ,opmode(0, 0, OpArgR, OpArgN, iAsBx)		/* OP_JMP */
 ,opmode(1, 0, OpArgK, OpArgK, iABC)		/* OP_EQ */
 ,opmode(1, 0, OpArgK, OpArgK, iABC)		/* OP_LT */
 ,opmode(1, 0, OpArgK, OpArgK, iABC)		/* OP_LE */
 ,opmode(1, 1, OpArgR, OpArgU, iABC)		/* OP_TEST */
 ,opmode(1, 1, OpArgR, OpArgU, iABC)		/* OP_TESTSET */
 ,opmode(0, 1, OpArgU, OpArgU, iABC)		/* OP_CALL */
 ,opmode(0, 1, OpArgU, OpArgU, iABC)		/* OP_TAILCALL */
 ,opmode(0, 0, OpArgU, OpArgN, iABC)		/* OP_RETURN */
 ,opmode(0, 1, OpArgR, OpArgN, iAsBx)		/* OP_FORLOOP */
 ,opmode(0, 1, OpArgR, OpArgN, iAsBx)		/* OP_FORPREP */
 ,opmode(1, 0, OpArgN, OpArgU, iABC)		/* OP_TFORLOOP */
 ,opmode(0, 0, OpArgU, OpArgU, iABC)		/* OP_SETLIST */
 ,opmode(0, 0, OpArgN, OpArgN, iABC)		/* OP_CLOSE */
 ,opmode(0, 1, OpArgU, OpArgN, iABx)		/* OP_CLOSURE */
 ,opmode(0, 1, OpArgU, OpArgN, iABC)		/* OP_VARARG */
};

